<?xml version="1.0" encoding="UTF-8"?>
<C xmlns="http://www.example.org/Numberplan" N="Ethiopia" C="251"><A N="Addis Ababa" C="11" T="FIX" L="2"/><A N="Nazareth" C="22" T="FIX" L="2"/><A N="Harar" C="25" T="FIX" L="2"/><A N="Dessie" C="33" T="FIX" L="2"/><A N="Mekele" C="34" T="FIX" L="2"/><A N="Shashemene" C="46" T="FIX" L="2"/><A N="Jimma" C="47" T="FIX" L="2"/><A N="West Ethiopia" C="57" T="FIX" L="2"/><A N="Gonder" C="58" T="FIX" L="2"/><A N="-" C="91" T="MOB" L="0"/><A N="EthioMobile" C="91110" T="MOB" L="0"/><A N="EthioMobile" C="91111" T="MOB" L="0"/><A N="EthioMobile" C="91112" T="MOB" L="0"/><A N="EthioMobile" C="91113" T="MOB" L="0"/><A N="EthioMobile" C="91114" T="MOB" L="0"/><A N="EthioMobile" C="91115" T="MOB" L="0"/><A N="EthioMobile" C="91116" T="MOB" L="0"/><A N="EthioMobile" C="91117" T="MOB" L="0"/><A N="EthioMobile" C="91118" T="MOB" L="0"/><A N="EthioMobile" C="91119" T="MOB" L="0"/><A N="EthioMobile" C="91120" T="MOB" L="0"/><A N="EthioMobile" C="91121" T="MOB" L="0"/><A N="EthioMobile" C="91122" T="MOB" L="0"/><A N="EthioMobile" C="91123" T="MOB" L="0"/><A N="EthioMobile" C="91124" T="MOB" L="0"/><A N="EthioMobile" C="91125" T="MOB" L="0"/><A N="EthioMobile" C="91140" T="MOB" L="0"/><A N="EthioMobile" C="91141" T="MOB" L="0"/><A N="EthioMobile" C="91142" T="MOB" L="0"/><A N="EthioMobile" C="91143" T="MOB" L="0"/><A N="EthioMobile" C="91144" T="MOB" L="0"/><A N="EthioMobile" C="91145" T="MOB" L="0"/><A N="EthioMobile" C="91146" T="MOB" L="0"/><A N="EthioMobile" C="91147" T="MOB" L="0"/><A N="EthioMobile" C="91148" T="MOB" L="0"/><A N="EthioMobile" C="91149" T="MOB" L="0"/><A N="EthioMobile" C="91150" T="MOB" L="0"/><A N="EthioMobile" C="91160" T="MOB" L="0"/><A N="EthioMobile" C="91161" T="MOB" L="0"/><A N="EthioMobile" C="91162" T="MOB" L="0"/><A N="EthioMobile" C="91163" T="MOB" L="0"/><A N="EthioMobile" C="91164" T="MOB" L="0"/><A N="EthioMobile" C="91165" T="MOB" L="0"/><A N="EthioMobile" C="91166" T="MOB" L="0"/><A N="EthioMobile" C="91167" T="MOB" L="0"/><A N="EthioMobile" C="91168" T="MOB" L="0"/><A N="EthioMobile" C="91169" T="MOB" L="0"/><A N="EthioMobile" C="91184" T="MOB" L="0"/><A N="EthioMobile" C="91186" T="MOB" L="0"/><A N="EthioMobile" C="91187" T="MOB" L="0"/><A N="EthioMobile" C="91188" T="MOB" L="0"/><A N="EthioMobile" C="91189" T="MOB" L="0"/><A N="EthioMobile" C="91430" T="MOB" L="0"/><A N="EthioMobile" C="91431" T="MOB" L="0"/><A N="EthioMobile" C="91470" T="MOB" L="0"/><A N="EthioMobile" C="91471" T="MOB" L="0"/><A N="EthioMobile" C="91472" T="MOB" L="0"/><A N="EthioMobile" C="91532" T="MOB" L="0"/><A N="EthioMobile" C="91533" T="MOB" L="0"/><A N="EthioMobile" C="91573" T="MOB" L="0"/><A N="EthioMobile" C="91574" T="MOB" L="0"/><A N="EthioMobile" C="91575" T="MOB" L="0"/><A N="EthioMobile" C="91658" T="MOB" L="0"/><A N="EthioMobile" C="91682" T="MOB" L="0"/><A N="EthioMobile" C="91683" T="MOB" L="0"/><A N="EthioMobile" C="91755" T="MOB" L="0"/><A N="EthioMobile" C="91757" T="MOB" L="0"/><A N="EthioMobile" C="91780" T="MOB" L="0"/><A N="EthioMobile" C="91781" T="MOB" L="0"/><A N="EthioMobile" C="91834" T="MOB" L="0"/><A N="EthioMobile" C="91835" T="MOB" L="0"/><A N="EthioMobile" C="91876" T="MOB" L="0"/><A N="EthioMobile" C="91877" T="MOB" L="0"/><A N="-" C="92" T="MOB" L="0"/></C>